dockyter/__init__.py
dockyter/backend.py
dockyter/config.py
dockyter/magics.py
dockyter-0.3.5.dist-info/licenses/LICENSE
dockyter-0.3.5.dist-info/METADATA
dockyter-0.3.5.dist-info/WHEEL
dockyter-0.3.5.dist-info/top_level.txt
dockyter-0.3.5.dist-info/RECORD
