Metadata-Version: 2.4
Name: dockyter
Version: 0.3.5
Summary: Run heavy tools in Docker or via an API from Jupyter notebooks
Author-email: Simon Masserey <simasserey@gmail.com>
License-Expression: MIT
Project-URL: Homepage, https://github.com/Lunfeer/dockyter
Project-URL: Documentation, https://github.com/Lunfeer/dockyter/tree/main/docs
Project-URL: Source, https://github.com/Lunfeer/dockyter
Project-URL: Issues, https://github.com/Lunfeer/dockyter/issues
Classifier: Framework :: IPython
Classifier: Framework :: Jupyter
Classifier: Intended Audience :: Developers
Classifier: Programming Language :: Python :: 3
Classifier: Programming Language :: Python :: 3.12
Requires-Python: >=3.12
License-File: LICENSE
Requires-Dist: ipython>=9.8.0
Requires-Dist: requests>=2.32.5
Dynamic: license-file
